Workbook

Sheet Read me
A1: Endustry ERP sales sheet: how to use it
A2: Prepared 09-10-2026
A4: Leads | B4: One row per prospect. Fill the yellow cells: company, contact, phone, email, city, industry, MSME category, current system, pain point, whether they are actively looking, source and stage. White cells (Lead ID, Fit score, Priority) are formulas; do not type in them. The first 19 rows are real companies researched on 09-10-2026; the Notes column says where each contact came from.
A5: Industries | B5: The industries that need this solution, ranked by fit, with why they need it and which modules to show them. It also counts your leads and hot leads per industry.
A6: Find leads | B6: Where to collect phone numbers and emails properly, the signals that someone is actively looking, and five qualifying questions.
A7: Summary | B7: Live counts by priority, stage, buying intent, industry and source.
A8: Lists | B8: The dropdown choices and the points behind the Fit score. Blue numbers on yellow are the inputs you can change.
A9: Colour key | B9: Yellow cell = you type here. White cell with a value = calculated. Red follow-up date = overdue. Priority: red Hot, amber Warm, blue Cold.
A10: Important | B10: The 19 researched companies are prospects by industry and location only. Nobody has spoken to them: we do not know their size, what software they use, or whether they want an ERP. Phone numbers and emails are the ones each company publishes for business enquiries; 11 were read on the company website and 8 came from a search summary and must be confirmed. Contact person names are left blank on purpose.

Sheet Leads
A1: Endustry ERP: sales leads
A2: One row per prospect. Type in the yellow columns; Fit score and Priority are worked out for you. The first rows are researched companies; add new leads below them.
A4: Lead ID | B4: Date added | C4: Company | D4: Contact person | E4: Designation | F4: Phone | G4: Email | H4: City | I4: State | J4: Industry | K4: MSME category | L4: Employees | M4: Current system | N4: Main pain point | O4: Modules of interest | P4: Actively looking? | Q4: Lead source | R4: Stage | S4: Fit score (0-100) | T4: Priority | U4: Next action | V4: Next follow-up | W4: Owner | X4: Notes
A5: =IF($C5="","","L-"&TEXT(ROW()-4,"000")) -> L-001 | B5: 46304 | C5: Robocon CNC Pvt. Ltd. | F5: +91 75758 62828 | G5: info@roboconcnc.com | H5: Pune (Katraj) | I5: Maharashtra | J5: Engineering, fabrication and machining | K5: Not known | M5: Not known | P5: Not asked yet | Q5: Own research (company website) | R5: New | S5: =IF($C5="","",IFERROR(INDEX(Lists!$B$5:$B$16,MATCH(J5,Lists!$A$5:$A$16,0)),0)+IFERROR(INDEX(Lists!$E$5:$E$8,MATCH(K5,Lists!$D$5:$D$8,0)),0)+IFERROR(INDEX(Lists!$H$5:$H$11,MATCH(M5,Lists!$G$5:$G$11,0)),0)+IFERROR(INDEX(Lists!$K$5:$K$9,MATCH(P5,Lists!$J$5:$J$9,0)),0)) -> 57 | T5: =IF($C5="","",IF(AND(S5>=75,LEFT(P5,3)="Yes"),"Hot",IF(S5>=55,"Warm","Cold"))) -> Warm | U5: First call: introduce, ask the five qualifying questions | W5: Mohit | X5: Precision CNC machined parts; ISO 9001:2015. Contact details read from the company website on 09-10-2026. Source: https://roboconcnc.com/
A6: =IF($C6="","","L-"&TEXT(ROW()-4,"000")) -> L-002 | B6: 46304 | C6: Trimurti Enterprises | F6: +91 91122 19222 | G6: enq@trimurti-enterprises.com | H6: Pune (Bhosari MIDC) | I6: Maharashtra | J6: Engineering, fabrication and machining | K6: Not known | M6: Not known | P6: Not asked yet | Q6: Own research (company website) | R6: New | S6: =IF($C6="","",IFERROR(INDEX(Lists!$B$5:$B$16,MATCH(J6,Lists!$A$5:$A$16,0)),0)+IFERROR(INDEX(Lists!$E$5:$E$8,MATCH(K6,Lists!$D$5:$D$8,0)),0)+IFERROR(INDEX(Lists!$H$5:$H$11,MATCH(M6,Lists!$G$5:$G$11,0)),0)+IFERROR(INDEX(Lists!$K$5:$K$9,MATCH(P6,Lists!$J$5:$J$9,0)),0)) -> 57 | T6: =IF($C6="","",IF(AND(S6>=75,LEFT(P6,3)="Yes"),"Hot",IF(S6>=55,"Warm","Cold"))) -> Warm | U6: First call: introduce, ask the five qualifying questions | W6: Mohit | X6: CNC machined parts, gears and gearboxes. Contact details read from the company website on 09-10-2026. Source: https://www.trimurti-enterprises.com/cnc-machined-parts-components.php
A7: =IF($C7="","","L-"&TEXT(ROW()-4,"000")) -> L-003 | B7: 46304 | C7: Sahyadri Industries | F7: +91 98506 26307 | G7: info@sahyadriindustries.co.in | H7: Pune (Chinchwad, Chakan) | I7: Maharashtra | J7: Engineering, fabrication and machining | K7: Not known | M7: Not known | P7: Not asked yet | Q7: Own research (company website) | R7: New | S7: =IF($C7="","",IFERROR(INDEX(Lists!$B$5:$B$16,MATCH(J7,Lists!$A$5:$A$16,0)),0)+IFERROR(INDEX(Lists!$E$5:$E$8,MATCH(K7,Lists!$D$5:$D$8,0)),0)+IFERROR(INDEX(Lists!$H$5:$H$11,MATCH(M7,Lists!$G$5:$G$11,0)),0)+IFERROR(INDEX(Lists!$K$5:$K$9,MATCH(P7,Lists!$J$5:$J$9,0)),0)) -> 57 | T7: =IF($C7="","",IF(AND(S7>=75,LEFT(P7,3)="Yes"),"Hot",IF(S7>=55,"Warm","Cold"))) -> Warm | U7: First call: introduce, ask the five qualifying questions | W7: Mohit | X7: Sheet metal fabrication, pressed and machined components; ISO 9001:2015; two factory units. Contact details read from the company website on 09-10-2026. Source: https://www.sahyadriindustries.co.in/
A8: =IF($C8="","","L-"&TEXT(ROW()-4,"000")) -> L-004 | B8: 46304 | C8: Technomech | F8: +91 99229 91642 | H8: Pune (Hadapsar) | I8: Maharashtra | J8: Engineering, fabrication and machining | K8: Not known | M8: Not known | P8: Not asked yet | Q8: Own research (company website) | R8: New | S8: =IF($C8="","",IFERROR(INDEX(Lists!$B$5:$B$16,MATCH(J8,Lists!$A$5:$A$16,0)),0)+IFERROR(INDEX(Lists!$E$5:$E$8,MATCH(K8,Lists!$D$5:$D$8,0)),0)+IFERROR(INDEX(Lists!$H$5:$H$11,MATCH(M8,Lists!$G$5:$G$11,0)),0)+IFERROR(INDEX(Lists!$K$5:$K$9,MATCH(P8,Lists!$J$5:$J$9,0)),0)) -> 57 | T8: =IF($C8="","",IF(AND(S8>=75,LEFT(P8,3)="Yes"),"Hot",IF(S8>=55,"Warm","Cold"))) -> Warm | U8: First call: introduce, ask the five qualifying questions | W8: Mohit | X8: Sheet metal pressed components, fabricated sub-assemblies, shafts; ISO 9001:2015. No email published, website has an enquiry form. Contact details read from the company website on 09-10-2026. Source: https://www.technomechpune.com/
A9: =IF($C9="","","L-"&TEXT(ROW()-4,"000")) -> L-005 | B9: 46304 | C9: Primeline Components Pvt Ltd | F9: +91 91303 03006 | G9: sales@primelinecomponents.in | H9: Pune | I9: Maharashtra | J9: Engineering, fabrication and machining | K9: Not known | M9: Not known | P9: Not asked yet | Q9: Own research (company website) | R9: New | S9: =IF($C9="","",IFERROR(INDEX(Lists!$B$5:$B$16,MATCH(J9,Lists!$A$5:$A$16,0)),0)+IFERROR(INDEX(Lists!$E$5:$E$8,MATCH(K9,Lists!$D$5:$D$8,0)),0)+IFERROR(INDEX(Lists!$H$5:$H$11,MATCH(M9,Lists!$G$5:$G$11,0)),0)+IFERROR(INDEX(Lists!$K$5:$K$9,MATCH(P9,Lists!$J$5:$J$9,0)),0)) -> 57 | T9: =IF($C9="","",IF(AND(S9>=75,LEFT(P9,3)="Yes"),"Hot",IF(S9>=55,"Warm","Cold"))) -> Warm | U9: First call: introduce, ask the five qualifying questions | W9: Mohit | X9: CNC and VMC machined components, plastic moulding; set up in 2025, part of Abhang Group. Contact details read from the company website on 09-10-2026. Source: https://www.primelinecomponents.com/about-us
A10: =IF($C10="","","L-"&TEXT(ROW()-4,"000")) -> L-006 | B10: 46304 | C10: Raj Tools & Stamping Pvt. Ltd. | F10: +91 84080 00812 | G10: marketing@rajtools.co.in | H10: Pune (Chikhali) | I10: Maharashtra | J10: Auto components (Tier 2 / Tier 3) | K10: Not known | M10: Not known | P10: Not asked yet | Q10: Own research (company website) | R10: New | S10: =IF($C10="","",IFERROR(INDEX(Lists!$B$5:$B$16,MATCH(J10,Lists!$A$5:$A$16,0)),0)+IFERROR(INDEX(Lists!$E$5:$E$8,MATCH(K10,Lists!$D$5:$D$8,0)),0)+IFERROR(INDEX(Lists!$H$5:$H$11,MATCH(M10,Lists!$G$5:$G$11,0)),0)+IFERROR(INDEX(Lists!$K$5:$K$9,MATCH(P10,Lists!$J$5:$J$9,0)),0)) -> 57 | T10: =IF($C10="","",IF(AND(S10>=75,LEFT(P10,3)="Yes"),"Hot",IF(S10>=55,"Warm","Cold"))) -> Warm | U10: First call: introduce, ask the five qualifying questions | W10: Mohit | X10: Sheet metal press tools and stamped parts; ISO 9001:2015; started 2012. Contact details read from the company website on 09-10-2026. Source: https://www.rajtools.co.in/
A11: =IF($C11="","","L-"&TEXT(ROW()-4,"000")) -> L-007 | B11: 46304 | C11: Datsons Engineering Works Pvt. Ltd. | F11: +91 90110 97737 | H11: Pune (Bhosari, Chakan) | I11: Maharashtra | J11: Auto components (Tier 2 / Tier 3) | K11: Not known | M11: Not known | P11: Not asked yet | Q11: Own research (company website) | R11: New | S11: =IF($C11="","",IFERROR(INDEX(Lists!$B$5:$B$16,MATCH(J11,Lists!$A$5:$A$16,0)),0)+IFERROR(INDEX(Lists!$E$5:$E$8,MATCH(K11,Lists!$D$5:$D$8,0)),0)+IFERROR(INDEX(Lists!$H$5:$H$11,MATCH(M11,Lists!$G$5:$G$11,0)),0)+IFERROR(INDEX(Lists!$K$5:$K$9,MATCH(P11,Lists!$J$5:$J$9,0)),0)) -> 57 | T11: =IF($C11="","",IF(AND(S11>=75,LEFT(P11,3)="Yes"),"Hot",IF(S11>=55,"Warm","Cold"))) -> Warm | U11: First call: introduce, ask the five qualifying questions | W11: Mohit | X11: Sheet metal press parts for auto and non-auto; est. 1983; two units. Sales number shown; no email published, website has an enquiry form. Contact details read from the company website on 09-10-2026. Source: https://www.datsonsengg.com/index.html
A12: =IF($C12="","","L-"&TEXT(ROW()-4,"000")) -> L-008 | B12: 46304 | C12: Devchhaya Group Of Industries | F12: +91 93729 65739 | G12: enquiry@devchhayagroup.in | H12: Pune (Chakan) | I12: Maharashtra | J12: Auto components (Tier 2 / Tier 3) | K12: Not known | M12: Not known | P12: Not asked yet | Q12: Own research (company website) | R12: New | S12: =IF($C12="","",IFERROR(INDEX(Lists!$B$5:$B$16,MATCH(J12,Lists!$A$5:$A$16,0)),0)+IFERROR(INDEX(Lists!$E$5:$E$8,MATCH(K12,Lists!$D$5:$D$8,0)),0)+IFERROR(INDEX(Lists!$H$5:$H$11,MATCH(M12,Lists!$G$5:$G$11,0)),0)+IFERROR(INDEX(Lists!$K$5:$K$9,MATCH(P12,Lists!$J$5:$J$9,0)),0)) -> 57 | T12: =IF($C12="","",IF(AND(S12>=75,LEFT(P12,3)="Yes"),"Hot",IF(S12>=55,"Warm","Cold"))) -> Warm | U12: First call: introduce, ask the five qualifying questions | W12: Mohit | X12: Automotive sheet metal components and assemblies. Site states 440+ employees across three units, so likely above our target size. Contact details read from the company website on 09-10-2026. Source: https://www.devchhayagroup.in/sheet-metal-automotive-components-assemblies.php
A13: =IF($C13="","","L-"&TEXT(ROW()-4,"000")) -> L-009 | B13: 46304 | C13: Perfect Auto Plast | F13: +91 98902 56650 | G13: perfectautoplast@gmail.com | H13: Pune (Katraj) | I13: Maharashtra | J13: Plastics, moulding and packaging | K13: Not known | M13: Not known | P13: Not asked yet | Q13: Own research (company website) | R13: New | S13: =IF($C13="","",IFERROR(INDEX(Lists!$B$5:$B$16,MATCH(J13,Lists!$A$5:$A$16,0)),0)+IFERROR(INDEX(Lists!$E$5:$E$8,MATCH(K13,Lists!$D$5:$D$8,0)),0)+IFERROR(INDEX(Lists!$H$5:$H$11,MATCH(M13,Lists!$G$5:$G$11,0)),0)+IFERROR(INDEX(Lists!$K$5:$K$9,MATCH(P13,Lists!$J$5:$J$9,0)),0)) -> 49 | T13: =IF($C13="","",IF(AND(S13>=75,LEFT(P13,3)="Yes"),"Hot",IF(S13>=55,"Warm","Cold"))) -> Cold | U13: First call: introduce, ask the five qualifying questions | W13: Mohit | X13: Plastic injection moulded parts, insert moulding, fuel strainers; ISO 9001:2015. Contact details read from the company website on 09-10-2026. Source: https://www.perfectautoplast.in/plastic-injection-moulding-part-in-pune.php
A14: =IF($C14="","","L-"&TEXT(ROW()-4,"000")) -> L-010 | B14: 46304 | C14: Maniar Plast | F14: +91 96894 91793 | G14: info@maniarplast.com | H14: Pune (Koregaon Bhima) | I14: Maharashtra | J14: Plastics, moulding and packaging | K14: Not known | M14: Not known | P14: Not asked yet | Q14: Own research (company website) | R14: New | S14: =IF($C14="","",IFERROR(INDEX(Lists!$B$5:$B$16,MATCH(J14,Lists!$A$5:$A$16,0)),0)+IFERROR(INDEX(Lists!$E$5:$E$8,MATCH(K14,Lists!$D$5:$D$8,0)),0)+IFERROR(INDEX(Lists!$H$5:$H$11,MATCH(M14,Lists!$G$5:$G$11,0)),0)+IFERROR(INDEX(Lists!$K$5:$K$9,MATCH(P14,Lists!$J$5:$J$9,0)),0)) -> 49 | T14: =IF($C14="","",IF(AND(S14>=75,LEFT(P14,3)="Yes"),"Hot",IF(S14>=55,"Warm","Cold"))) -> Cold | U14: First call: introduce, ask the five qualifying questions | W14: Mohit | X14: Injection moulded parts for automotive, medical and FMCG; ISO 9001:2015 and ISO 13485. Contact details read from the company website on 09-10-2026. Source: https://maniarplast.com/services/plastic-injection-molding/
A15: =IF($C15="","","L-"&TEXT(ROW()-4,"000")) -> L-011 | B15: 46304 | C15: Aim Mouldplast Private Limited | F15: +91 98508 07899 | G15: response@aimplastindia.com | H15: Pune (Talawade) | I15: Maharashtra | J15: Plastics, moulding and packaging | K15: Not known | M15: Not known | P15: Not asked yet | Q15: Own research (company website) | R15: New | S15: =IF($C15="","",IFERROR(INDEX(Lists!$B$5:$B$16,MATCH(J15,Lists!$A$5:$A$16,0)),0)+IFERROR(INDEX(Lists!$E$5:$E$8,MATCH(K15,Lists!$D$5:$D$8,0)),0)+IFERROR(INDEX(Lists!$H$5:$H$11,MATCH(M15,Lists!$G$5:$G$11,0)),0)+IFERROR(INDEX(Lists!$K$5:$K$9,MATCH(P15,Lists!$J$5:$J$9,0)),0)) -> 49 | T15: =IF($C15="","",IF(AND(S15>=75,LEFT(P15,3)="Yes"),"Hot",IF(S15>=55,"Warm","Cold"))) -> Cold | U15: First call: introduce, ask the five qualifying questions | W15: Mohit | X15: Moulds and precision moulded automotive parts; est. 1996; IATF 16949. Contact details read from the company website on 09-10-2026. Source: https://www.aimplastindia.com/index.html
A16: =IF($C16="","","L-"&TEXT(ROW()-4,"000")) -> L-012 | B16: 46304 | C16: Eshaan Enterprises | F16: +91 91365 99447 | G16: info@eshaanentp.com | H16: Pune (Somatane Phata) | I16: Maharashtra | J16: Engineering, fabrication and machining | K16: Not known | M16: Not known | P16: Not asked yet | Q16: Own research (company website) | R16: New | S16: =IF($C16="","",IFERROR(INDEX(Lists!$B$5:$B$16,MATCH(J16,Lists!$A$5:$A$16,0)),0)+IFERROR(INDEX(Lists!$E$5:$E$8,MATCH(K16,Lists!$D$5:$D$8,0)),0)+IFERROR(INDEX(Lists!$H$5:$H$11,MATCH(M16,Lists!$G$5:$G$11,0)),0)+IFERROR(INDEX(Lists!$K$5:$K$9,MATCH(P16,Lists!$J$5:$J$9,0)),0)) -> 57 | T16: =IF($C16="","",IF(AND(S16>=75,LEFT(P16,3)="Yes"),"Hot",IF(S16>=55,"Warm","Cold"))) -> Warm | U16: First call: introduce, ask the five qualifying questions | W16: Mohit | X16: Structural and heavy fabrication; ISO 9001:2015. Contact details from a search summary of the company website on 09-10-2026; website not opened, confirm before use. Source: https://www.eshaanentp.com/structural-fabrication-in-pune.php
A17: =IF($C17="","","L-"&TEXT(ROW()-4,"000")) -> L-013 | B17: 46304 | C17: Shreeniwas Casttech Industries | F17: +91 89831 88989 | G17: info@shreeniwascasttech.in | H17: Pune (Chakan) | I17: Maharashtra | J17: Castings and forgings | K17: Not known | M17: Not known | P17: Not asked yet | Q17: Own research (company website) | R17: New | S17: =IF($C17="","",IFERROR(INDEX(Lists!$B$5:$B$16,MATCH(J17,Lists!$A$5:$A$16,0)),0)+IFERROR(INDEX(Lists!$E$5:$E$8,MATCH(K17,Lists!$D$5:$D$8,0)),0)+IFERROR(INDEX(Lists!$H$5:$H$11,MATCH(M17,Lists!$G$5:$G$11,0)),0)+IFERROR(INDEX(Lists!$K$5:$K$9,MATCH(P17,Lists!$J$5:$J$9,0)),0)) -> 49 | T17: =IF($C17="","",IF(AND(S17>=75,LEFT(P17,3)="Yes"),"Hot",IF(S17>=55,"Warm","Cold"))) -> Cold | U17: First call: introduce, ask the five qualifying questions | W17: Mohit | X17: Aluminium gravity die castings, CNC machined components. Contact details from a search summary of the company website on 09-10-2026; website not opened, confirm before use. Source: https://www.shreeniwascasttech.in/
A18: =IF($C18="","","L-"&TEXT(ROW()-4,"000")) -> L-014 | B18: 46304 | C18: Sahayog Founders & Engineers | F18: 020 2712 2371 | G18: info@sahayogfounders.com | H18: Pune (Bhosari MIDC) | I18: Maharashtra | J18: Castings and forgings | K18: Not known | M18: Not known | P18: Not asked yet | Q18: Own research (company website) | R18: New | S18: =IF($C18="","",IFERROR(INDEX(Lists!$B$5:$B$16,MATCH(J18,Lists!$A$5:$A$16,0)),0)+IFERROR(INDEX(Lists!$E$5:$E$8,MATCH(K18,Lists!$D$5:$D$8,0)),0)+IFERROR(INDEX(Lists!$H$5:$H$11,MATCH(M18,Lists!$G$5:$G$11,0)),0)+IFERROR(INDEX(Lists!$K$5:$K$9,MATCH(P18,Lists!$J$5:$J$9,0)),0)) -> 49 | T18: =IF($C18="","",IF(AND(S18>=75,LEFT(P18,3)="Yes"),"Hot",IF(S18>=55,"Warm","Cold"))) -> Cold | U18: First call: introduce, ask the five qualifying questions | W18: Mohit | X18: Aluminium die casting with machining; est. 1990. Contact details from a search summary of the company website on 09-10-2026; website not opened, confirm before use. Source: http://sahayogfounders.com/
A19: =IF($C19="","","L-"&TEXT(ROW()-4,"000")) -> L-015 | B19: 46304 | C19: Versatile Alucast Pvt. Ltd. | F19: +91 90903 04848 | G19: marketing@versatilegroup.co.in | H19: Kolhapur (Shiroli MIDC) | I19: Maharashtra | J19: Castings and forgings | K19: Not known | M19: Not known | P19: Not asked yet | Q19: Own research (company website) | R19: New | S19: =IF($C19="","",IFERROR(INDEX(Lists!$B$5:$B$16,MATCH(J19,Lists!$A$5:$A$16,0)),0)+IFERROR(INDEX(Lists!$E$5:$E$8,MATCH(K19,Lists!$D$5:$D$8,0)),0)+IFERROR(INDEX(Lists!$H$5:$H$11,MATCH(M19,Lists!$G$5:$G$11,0)),0)+IFERROR(INDEX(Lists!$K$5:$K$9,MATCH(P19,Lists!$J$5:$J$9,0)),0)) -> 49 | T19: =IF($C19="","",IF(AND(S19>=75,LEFT(P19,3)="Yes"),"Hot",IF(S19>=55,"Warm","Cold"))) -> Cold | U19: First call: introduce, ask the five qualifying questions | W19: Mohit | X19: Aluminium castings with in-house machining. Contact details from a search summary of the company website on 09-10-2026; website not opened, confirm before use. Source: https://www.versatilegroup.co.in/aluminium-casting-foundry-kolhapur.php
A20: =IF($C20="","","L-"&TEXT(ROW()-4,"000")) -> L-016 | B20: 46304 | C20: Hindustan Castings | F20: +91 98812 48251 | G20: response@hindustancastings.com | H20: Kolhapur (Gokul Shirgaon MIDC) | I20: Maharashtra | J20: Castings and forgings | K20: Not known | M20: Not known | P20: Not asked yet | Q20: Own research (company website) | R20: New | S20: =IF($C20="","",IFERROR(INDEX(Lists!$B$5:$B$16,MATCH(J20,Lists!$A$5:$A$16,0)),0)+IFERROR(INDEX(Lists!$E$5:$E$8,MATCH(K20,Lists!$D$5:$D$8,0)),0)+IFERROR(INDEX(Lists!$H$5:$H$11,MATCH(M20,Lists!$G$5:$G$11,0)),0)+IFERROR(INDEX(Lists!$K$5:$K$9,MATCH(P20,Lists!$J$5:$J$9,0)),0)) -> 49 | T20: =IF($C20="","",IF(AND(S20>=75,LEFT(P20,3)="Yes"),"Hot",IF(S20>=55,"Warm","Cold"))) -> Cold | U20: First call: introduce, ask the five qualifying questions | W20: Mohit | X20: Aluminium die castings and precision components; two units. Contact details from a search summary of the company website on 09-10-2026; website not opened, confirm before use. Source: https://www.hindustancastings.com/index.html
A21: =IF($C21="","","L-"&TEXT(ROW()-4,"000")) -> L-017 | B21: 46304 | C21: Samarth Foundry Services Pvt. Ltd. | F21: +91 99229 30789 | G21: mktg@samarthfoundry.com | H21: Kolhapur (Hatkanangale) | I21: Maharashtra | J21: Castings and forgings | K21: Not known | M21: Not known | P21: Not asked yet | Q21: Own research (company website) | R21: New | S21: =IF($C21="","",IFERROR(INDEX(Lists!$B$5:$B$16,MATCH(J21,Lists!$A$5:$A$16,0)),0)+IFERROR(INDEX(Lists!$E$5:$E$8,MATCH(K21,Lists!$D$5:$D$8,0)),0)+IFERROR(INDEX(Lists!$H$5:$H$11,MATCH(M21,Lists!$G$5:$G$11,0)),0)+IFERROR(INDEX(Lists!$K$5:$K$9,MATCH(P21,Lists!$J$5:$J$9,0)),0)) -> 49 | T21: =IF($C21="","",IF(AND(S21>=75,LEFT(P21,3)="Yes"),"Hot",IF(S21>=55,"Warm","Cold"))) -> Cold | U21: First call: introduce, ask the five qualifying questions | W21: Mohit | X21: Machined iron castings, 100 to 500 kg; ISO 9001:2015. Contact details from a search summary of the company website on 09-10-2026; website not opened, confirm before use. Source: https://www.samarthfoundry.com/ci-casting-pune.php
A22: =IF($C22="","","L-"&TEXT(ROW()-4,"000")) -> L-018 | B22: 46304 | C22: Finecast | F22: +91 90755 51099 | G22: sales@finecastkop.com | H22: Kolhapur (Gokul Shirgaon) | I22: Maharashtra | J22: Castings and forgings | K22: Not known | M22: Not known | P22: Not asked yet | Q22: Own research (company website) | R22: New | S22: =IF($C22="","",IFERROR(INDEX(Lists!$B$5:$B$16,MATCH(J22,Lists!$A$5:$A$16,0)),0)+IFERROR(INDEX(Lists!$E$5:$E$8,MATCH(K22,Lists!$D$5:$D$8,0)),0)+IFERROR(INDEX(Lists!$H$5:$H$11,MATCH(M22,Lists!$G$5:$G$11,0)),0)+IFERROR(INDEX(Lists!$K$5:$K$9,MATCH(P22,Lists!$J$5:$J$9,0)),0)) -> 49 | T22: =IF($C22="","",IF(AND(S22>=75,LEFT(P22,3)="Yes"),"Hot",IF(S22>=55,"Warm","Cold"))) -> Cold | U22: First call: introduce, ask the five qualifying questions | W22: Mohit | X22: CI foundry with machine shop for automotive, hydraulic and pump castings. Contact details from a search summary of the company website on 09-10-2026; website not opened, confirm before use. Source: https://www.finecastkop.com/ci-casting-foundry.php
A23: =IF($C23="","","L-"&TEXT(ROW()-4,"000")) -> L-019 | B23: 46304 | C23: Kolhapur Metals LLP | F23: +91 99234 57739 | G23: marketing@kolhapurmetals.com | H23: Kolhapur (Gokul Shirgaon MIDC) | I23: Maharashtra | J23: Castings and forgings | K23: Not known | M23: Not known | P23: Not asked yet | Q23: Own research (company website) | R23: New | S23: =IF($C23="","",IFERROR(INDEX(Lists!$B$5:$B$16,MATCH(J23,Lists!$A$5:$A$16,0)),0)+IFERROR(INDEX(Lists!$E$5:$E$8,MATCH(K23,Lists!$D$5:$D$8,0)),0)+IFERROR(INDEX(Lists!$H$5:$H$11,MATCH(M23,Lists!$G$5:$G$11,0)),0)+IFERROR(INDEX(Lists!$K$5:$K$9,MATCH(P23,Lists!$J$5:$J$9,0)),0)) -> 49 | T23: =IF($C23="","",IF(AND(S23>=75,LEFT(P23,3)="Yes"),"Hot",IF(S23>=55,"Warm","Cold"))) -> Cold | U23: First call: introduce, ask the five qualifying questions | W23: Mohit | X23: Grey iron, SG iron, SiMo and ADI castings with machining. Contact details from a search summary of the company website on 09-10-2026; website not opened, confirm before use. Source: https://www.kolhapurmetals.com/
A24: =IF($C24="","","L-"&TEXT(ROW()-4,"000")) | S24: =IF($C24="","",IFERROR(INDEX(Lists!$B$5:$B$16,MATCH(J24,Lists!$A$5:$A$16,0)),0)+IFERROR(INDEX(Lists!$E$5:$E$8,MATCH(K24,Lists!$D$5:$D$8,0)),0)+IFERROR(INDEX(Lists!$H$5:$H$11,MATCH(M24,Lists!$G$5:$G$11,0)),0)+IFERROR(INDEX(Lists!$K$5:$K$9,MATCH(P24,Lists!$J$5:$J$9,0)),0)) | T24: =IF($C24="","",IF(AND(S24>=75,LEFT(P24,3)="Yes"),"Hot",IF(S24>=55,"Warm","Cold")))
A25: =IF($C25="","","L-"&TEXT(ROW()-4,"000")) | S25: =IF($C25="","",IFERROR(INDEX(Lists!$B$5:$B$16,MATCH(J25,Lists!$A$5:$A$16,0)),0)+IFERROR(INDEX(Lists!$E$5:$E$8,MATCH(K25,Lists!$D$5:$D$8,0)),0)+IFERROR(INDEX(Lists!$H$5:$H$11,MATCH(M25,Lists!$G$5:$G$11,0)),0)+IFERROR(INDEX(Lists!$K$5:$K$9,MATCH(P25,Lists!$J$5:$J$9,0)),0)) | T25: =IF($C25="","",IF(AND(S25>=75,LEFT(P25,3)="Yes"),"Hot",IF(S25>=55,"Warm","Cold")))
A26: =IF($C26="","","L-"&TEXT(ROW()-4,"000")) | S26: =IF($C26="","",IFERROR(INDEX(Lists!$B$5:$B$16,MATCH(J26,Lists!$A$5:$A$16,0)),0)+IFERROR(INDEX(Lists!$E$5:$E$8,MATCH(K26,Lists!$D$5:$D$8,0)),0)+IFERROR(INDEX(Lists!$H$5:$H$11,MATCH(M26,Lists!$G$5:$G$11,0)),0)+IFERROR(INDEX(Lists!$K$5:$K$9,MATCH(P26,Lists!$J$5:$J$9,0)),0)) | T26: =IF($C26="","",IF(AND(S26>=75,LEFT(P26,3)="Yes"),"Hot",IF(S26>=55,"Warm","Cold")))
A27: =IF($C27="","","L-"&TEXT(ROW()-4,"000")) | S27: =IF($C27="","",IFERROR(INDEX(Lists!$B$5:$B$16,MATCH(J27,Lists!$A$5:$A$16,0)),0)+IFERROR(INDEX(Lists!$E$5:$E$8,MATCH(K27,Lists!$D$5:$D$8,0)),0)+IFERROR(INDEX(Lists!$H$5:$H$11,MATCH(M27,Lists!$G$5:$G$11,0)),0)+IFERROR(INDEX(Lists!$K$5:$K$9,MATCH(P27,Lists!$J$5:$J$9,0)),0)) | T27: =IF($C27="","",IF(AND(S27>=75,LEFT(P27,3)="Yes"),"Hot",IF(S27>=55,"Warm","Cold")))
A28: =IF($C28="","","L-"&TEXT(ROW()-4,"000")) | S28: =IF($C28="","",IFERROR(INDEX(Lists!$B$5:$B$16,MATCH(J28,Lists!$A$5:$A$16,0)),0)+IFERROR(INDEX(Lists!$E$5:$E$8,MATCH(K28,Lists!$D$5:$D$8,0)),0)+IFERROR(INDEX(Lists!$H$5:$H$11,MATCH(M28,Lists!$G$5:$G$11,0)),0)+IFERROR(INDEX(Lists!$K$5:$K$9,MATCH(P28,Lists!$J$5:$J$9,0)),0)) | T28: =IF($C28="","",IF(AND(S28>=75,LEFT(P28,3)="Yes"),"Hot",IF(S28>=55,"Warm","Cold")))
A29: =IF($C29="","","L-"&TEXT(ROW()-4,"000")) | S29: =IF($C29="","",IFERROR(INDEX(Lists!$B$5:$B$16,MATCH(J29,Lists!$A$5:$A$16,0)),0)+IFERROR(INDEX(Lists!$E$5:$E$8,MATCH(K29,Lists!$D$5:$D$8,0)),0)+IFERROR(INDEX(Lists!$H$5:$H$11,MATCH(M29,Lists!$G$5:$G$11,0)),0)+IFERROR(INDEX(Lists!$K$5:$K$9,MATCH(P29,Lists!$J$5:$J$9,0)),0)) | T29: =IF($C29="","",IF(AND(S29>=75,LEFT(P29,3)="Yes"),"Hot",IF(S29>=55,"Warm","Cold")))
A30: =IF($C30="","","L-"&TEXT(ROW()-4,"000")) | S30: =IF($C30="","",IFERROR(INDEX(Lists!$B$5:$B$16,MATCH(J30,Lists!$A$5:$A$16,0)),0)+IFERROR(INDEX(Lists!$E$5:$E$8,MATCH(K30,Lists!$D$5:$D$8,0)),0)+IFERROR(INDEX(Lists!$H$5:$H$11,MATCH(M30,Lists!$G$5:$G$11,0)),0)+IFERROR(INDEX(Lists!$K$5:$K$9,MATCH(P30,Lists!$J$5:$J$9,0)),0)) | T30: =IF($C30="","",IF(AND(S30>=75,LEFT(P30,3)="Yes"),"Hot",IF(S30>=55,"Warm","Cold")))
A31: =IF($C31="","","L-"&TEXT(ROW()-4,"000")) | S31: =IF($C31="","",IFERROR(INDEX(Lists!$B$5:$B$16,MATCH(J31,Lists!$A$5:$A$16,0)),0)+IFERROR(INDEX(Lists!$E$5:$E$8,MATCH(K31,Lists!$D$5:$D$8,0)),0)+IFERROR(INDEX(Lists!$H$5:$H$11,MATCH(M31,Lists!$G$5:$G$11,0)),0)+IFERROR(INDEX(Lists!$K$5:$K$9,MATCH(P31,Lists!$J$5:$J$9,0)),0)) | T31: =IF($C31="","",IF(AND(S31>=75,LEFT(P31,3)="Yes"),"Hot",IF(S31>=55,"Warm","Cold")))
A32: =IF($C32="","","L-"&TEXT(ROW()-4,"000")) | S32: =IF($C32="","",IFERROR(INDEX(Lists!$B$5:$B$16,MATCH(J32,Lists!$A$5:$A$16,0)),0)+IFERROR(INDEX(Lists!$E$5:$E$8,MATCH(K32,Lists!$D$5:$D$8,0)),0)+IFERROR(INDEX(Lists!$H$5:$H$11,MATCH(M32,Lists!$G$5:$G$11,0)),0)+IFERROR(INDEX(Lists!$K$5:$K$9,MATCH(P32,Lists!$J$5:$J$9,0)),0)) | T32: =IF($C32="","",IF(AND(S32>=75,LEFT(P32,3)="Yes"),"Hot",IF(S32>=55,"Warm","Cold")))
A33: =IF($C33="","","L-"&TEXT(ROW()-4,"000")) | S33: =IF($C33="","",IFERROR(INDEX(Lists!$B$5:$B$16,MATCH(J33,Lists!$A$5:$A$16,0)),0)+IFERROR(INDEX(Lists!$E$5:$E$8,MATCH(K33,Lists!$D$5:$D$8,0)),0)+IFERROR(INDEX(Lists!$H$5:$H$11,MATCH(M33,Lists!$G$5:$G$11,0)),0)+IFERROR(INDEX(Lists!$K$5:$K$9,MATCH(P33,Lists!$J$5:$J$9,0)),0)) | T33: =IF($C33="","",IF(AND(S33>=75,LEFT(P33,3)="Yes"),"Hot",IF(S33>=55,"Warm","Cold")))
A34: =IF($C34="","","L-"&TEXT(ROW()-4,"000")) | S34: =IF($C34="","",IFERROR(INDEX(Lists!$B$5:$B$16,MATCH(J34,Lists!$A$5:$A$16,0)),0)+IFERROR(INDEX(Lists!$E$5:$E$8,MATCH(K34,Lists!$D$5:$D$8,0)),0)+IFERROR(INDEX(Lists!$H$5:$H$11,MATCH(M34,Lists!$G$5:$G$11,0)),0)+IFERROR(INDEX(Lists!$K$5:$K$9,MATCH(P34,Lists!$J$5:$J$9,0)),0)) | T34: =IF($C34="","",IF(AND(S34>=75,LEFT(P34,3)="Yes"),"Hot",IF(S34>=55,"Warm","Cold")))
A35: =IF($C35="","","L-"&TEXT(ROW()-4,"000")) | S35: =IF($C35="","",IFERROR(INDEX(Lists!$B$5:$B$16,MATCH(J35,Lists!$A$5:$A$16,0)),0)+IFERROR(INDEX(Lists!$E$5:$E$8,MATCH(K35,Lists!$D$5:$D$8,0)),0)+IFERROR(INDEX(Lists!$H$5:$H$11,MATCH(M35,Lists!$G$5:$G$11,0)),0)+IFERROR(INDEX(Lists!$K$5:$K$9,MATCH(P35,Lists!$J$5:$J$9,0)),0)) | T35: =IF($C35="","",IF(AND(S35>=75,LEFT(P35,3)="Yes"),"Hot",IF(S35>=55,"Warm","Cold")))
... A304: =IF($C304="","","L-"&TEXT(ROW()-4,"000")) | S304: =IF($C304="","",IFERROR(INDEX(Lists!$B$5:$B$16,MATCH(J304,Lists!$A$5:$A$16,0)),0)+IFERROR(INDEX(Lists!$E$5:$E$8,MATCH(K304,Lists!$D$5:$D$8,0)),0)+IFERROR(INDEX(Lists!$H$5:$H$11,MATCH(M304,Lists!$G$5:$G$11,0)),0)+IFERROR(INDEX(Lists!$K$5:$K$9,MATCH(P304,Lists!$J$5:$J$9,0)),0)) | T304: =IF($C304="","",IF(AND(S304>=75,LEFT(P304,3)="Yes"),"Hot",IF(S304>=55,"Warm","Cold")))

Sheet Industries
A1: Which industries need this solution
A2: Ranked by fit with what Endustry ERP does today. Fit (1 to 5) is our judgement from the BRD, to be checked against real customer conversations.
A4: Rank | B4: Industry | C4: Fit (1-5) | D4: Typical products | E4: Why they need it | F4: Modules that matter most | G4: Status in our product plan | H4: Where they cluster (indicative) | I4: Leads in sheet | J4: Hot leads
A5: 1 | B5: Engineering, fabrication and machining | C5: 5 | D5: Machined parts, fabricated structures, jobs to drawing | E5: Make-to-order jobs, paper job cards, unknown cost per job, heat-number traceability, job work for plating and heat treatment | F5: Production, job cards, BOM and costing, inventory with batches, quality | G5: Phase 1 launch template | H5: Pune, Rajkot, Coimbatore, Ludhiana, Faridabad, Bengaluru (Peenya) | I5: =COUNTIF(Leads!$J$5:$J$304,B5) -> 6 | J5: =COUNTIFS(Leads!$J$5:$J$304,B5,Leads!$T$5:$T$304,"Hot") -> 0
A6: 2 | B6: Auto components (Tier 2 / Tier 3) | C6: 5 | D6: Turned parts, pressed parts, castings, rubber and plastic parts for OEMs | E6: OEM delivery schedules, rejection penalties, batch traceability demanded by customers, tight margins need true costing | F6: Sales orders, production, quality, costing, inventory | G6: Phase 1 launch template | H6: Pune (Chakan), Chennai, Gurugram-Manesar, Aurangabad, Hosur | I6: =COUNTIF(Leads!$J$5:$J$304,B6) -> 3 | J6: =COUNTIFS(Leads!$J$5:$J$304,B6,Leads!$T$5:$T$304,"Hot") -> 0
A7: 3 | B7: Plastics, moulding and packaging | C7: 4 | D7: Injection moulded parts, blow moulded containers, films, cartons | E7: Machine-hour costing, regrind and scrap, colour and size variants, frequent small orders | F7: Production, BOM with scrap, inventory, sales, costing | G7: Phase 1 launch template | H7: Daman, Vapi, Ahmedabad, Mumbai-Thane, Delhi NCR | I7: =COUNTIF(Leads!$J$5:$J$304,B7) -> 3 | J7: =COUNTIFS(Leads!$J$5:$J$304,B7,Leads!$T$5:$T$304,"Hot") -> 0
A8: 4 | B8: Food processing and formulations | C8: 4 | D8: Snacks, spices, bakery, beverages, nutraceuticals | E8: Batch and expiry control, quality release before sale, recipe (formula) costing, FSSAI traceability | F8: Inventory with batches, quality, BOM, production, sales | G8: BRD launch template (expiry tracking not built yet) | H8: Indore, Ahmedabad, Hyderabad, Kolhapur, Delhi NCR | I8: =COUNTIF(Leads!$J$5:$J$304,B8) -> 0 | J8: =COUNTIFS(Leads!$J$5:$J$304,B8,Leads!$T$5:$T$304,"Hot") -> 0
A9: 5 | B9: Castings and forgings | C9: 4 | D9: Iron and aluminium castings, forgings | E9: Heat-wise traceability, high rejection rates, melt and yield costing, job work for machining | F9: Production, quality, costing, inventory with batches | G9: Covered by engineering template | H9: Kolhapur, Rajkot, Coimbatore, Belgaum, Batala | I9: =COUNTIF(Leads!$J$5:$J$304,B9) -> 7 | J9: =COUNTIFS(Leads!$J$5:$J$304,B9,Leads!$T$5:$T$304,"Hot") -> 0
A10: 6 | B10: Textiles and garments | C10: 3 | D10: Fabric, garments, home textiles, processing houses | E10: Size and colour variants, job work for dyeing, printing and stitching, lot-wise tracking | F10: Inventory, production, purchase, sales | G10: BRD launch template (variants and job work not built yet) | H10: Tiruppur, Surat, Ludhiana, Ichalkaranji, Erode | I10: =COUNTIF(Leads!$J$5:$J$304,B10) -> 0 | J10: =COUNTIFS(Leads!$J$5:$J$304,B10,Leads!$T$5:$T$304,"Hot") -> 0
A11: 7 | B11: Chemicals and paints | C11: 3 | D11: Speciality chemicals, paints, adhesives, dyes | E11: Process (formula) BOM, batch traceability, quality testing of every batch | F11: Inventory with batches, quality, BOM, purchase | G11: Phase 2 template | H11: Vapi, Ankleshwar, Dahej, Navi Mumbai, Vadodara | I11: =COUNTIF(Leads!$J$5:$J$304,B11) -> 0 | J11: =COUNTIFS(Leads!$J$5:$J$304,B11,Leads!$T$5:$T$304,"Hot") -> 0
A12: 8 | B12: Electricals and cables | C12: 3 | D12: Wires, cables, switchgear, panels, transformers | E12: Copper and aluminium price swings change cost daily, length-based stock, order-wise costing | F12: Costing, inventory, production, purchase | G12: Phase 2 template | H12: Delhi NCR, Vadodara, Bengaluru, Silvassa | I12: =COUNTIF(Leads!$J$5:$J$304,B12) -> 0 | J12: =COUNTIFS(Leads!$J$5:$J$304,B12,Leads!$T$5:$T$304,"Hot") -> 0
A13: 9 | B13: Rubber and polymer products | C13: 3 | D13: Rubber mouldings, hoses, gaskets, tyres retread | E13: Compound recipe costing, batch curing records, OEM quality requirements | F13: BOM, production, quality, inventory | G13: Not a named template | H13: Kottayam, Pune, Jalandhar, Chennai | I13: =COUNTIF(Leads!$J$5:$J$304,B13) -> 0 | J13: =COUNTIFS(Leads!$J$5:$J$304,B13,Leads!$T$5:$T$304,"Hot") -> 0
A14: 10 | B14: Furniture and wood products | C14: 2 | D14: Modular furniture, doors, panels | E14: Order-wise costing and cut-plan wastage; many are project based rather than repeat production | F14: Sales orders, BOM, production, purchase | G14: Not a named template | H14: Jodhpur, Bengaluru, Kirti Nagar (Delhi), Mumbai | I14: =COUNTIF(Leads!$J$5:$J$304,B14) -> 0 | J14: =COUNTIFS(Leads!$J$5:$J$304,B14,Leads!$T$5:$T$304,"Hot") -> 0
A15: 11 | B15: Pharma formulations (small) | C15: 2 | D15: Tablets, syrups, ointments under loan licence or own brand | E15: Strong need for batch, expiry and QC release, but regulated validation is outside the product scope | F15: Inventory with batches, quality, production | G15: Out of scope for regulated validation | H15: Baddi, Ahmedabad, Hyderabad, Haridwar | I15: =COUNTIF(Leads!$J$5:$J$304,B15) -> 0 | J15: =COUNTIFS(Leads!$J$5:$J$304,B15,Leads!$T$5:$T$304,"Hot") -> 0
A16: 12 | B16: Other manufacturing | C16: 2 | D16: Anything not listed above | E16: Qualify on the call | F16: Qualify on the call | G16: Not a named template | I16: =COUNTIF(Leads!$J$5:$J$304,B16) -> 0 | J16: =COUNTIFS(Leads!$J$5:$J$304,B16,Leads!$T$5:$T$304,"Hot") -> 0
A18: Sources: industries, pain points and launch templates are from Endustry_ERP_BRD.docx (sections 2.2, 4, 5 and 8.21). Fit scores and cluster cities are our own working assumptions and are not verified market data. Target size from the BRD: turnover Rs 2 crore to Rs 100 crore, 10 to 250 employees.

Sheet Find leads
A1: Where to find leads, and how to tell who is actively looking
A2: Collect phone numbers and emails from the business itself or from sources where it published them for enquiries. Do not buy scraped lists.
A4: Source | B4: What you get | C4: How to use it | D4: Signal that they are actively looking
A5: Your own website and Instagram | B5: Name, phone and email given by the prospect | C5: Add a "Book a demo" form and a WhatsApp button; put the link in the reel and carousel captions | D5: They filled the form or messaged you. This is the strongest signal.
A6: CA firms and Tally partners | B6: Warm introductions to their manufacturing clients | C6: Offer a referral share; ask each partner for clients who complain about stock, costing or production | D6: The CA says the client has outgrown Tally or asked about an ERP
A7: Existing customers | B7: Referrals to suppliers, job workers and neighbours in the same estate | C7: Ask after every successful go-live; offer a month free per referral | D7: Referred owner asks for a demo
A8: Industry associations and estates | B8: Member directories of MIDC / GIDC estates, CII, MCCIA, local chambers, sector bodies | C8: Join, attend meets, sponsor a session; use the published member directory for the industry and city | D8: Member asks questions at a session or visits your stall
A9: IndiaMART / TradeIndia | B9: Manufacturers by product and city, with the enquiry number they published | C9: Search by product in a target cluster; contact as a vendor introduction, not bulk messaging | D9: They have posted a requirement for ERP, inventory or production software
A10: LinkedIn | B10: Owners, plant heads and finance heads of small manufacturers | C10: Search by title and city; send a short personal note with the reel | D10: Posts about hiring planners or storekeepers, expansion, or software frustration
A11: Trade expos | B11: Visiting cards from exhibitors in your target industries | C11: Walk the stalls of small exhibitors; note their industry and pain on the card | D11: Asks about price and go-live time on the spot
A12: Udyam and GST public search | B12: Confirmation that a business is a registered MSME and its category | C12: Use to verify a lead and fill the MSME category; it does not provide contact lists | D12: Not a buying signal; a qualification check
A14: Five questions that tell you if a lead is actively looking
A15: 1. What made you look for software now? (a trigger: audit, lost order, new customer demand, growth)
A16: 2. Who else is involved in the decision, and have they agreed a budget?
A17: 3. By when do you want it running?
A18: 4. What are you using today, and what is the one thing it cannot do?
A19: 5. Have you seen demos of other products? Which ones?
A21: Before calling or emailing: commercial calls and SMS to numbers on the Do Not Disturb registry are restricted under TRAI rules, and personal data (a named person's mobile or email) falls under the Digital Personal Data Protection Act, 2023. Contact businesses on details they published for business enquiries, say where you got them, and stop when asked. Check the current rules before any bulk outreach.

Sheet Summary
A1: Pipeline summary
A2: Counts update automatically from the Leads sheet.
A4: Headline | B4: Count | D4: By industry | E4: Leads
A5: Total leads | B5: =COUNTA(Leads!$C$5:$C$304) -> 19 | D5: Engineering, fabrication and machining | E5: =COUNTIF(Leads!$J$5:$J$304,D5) -> 6
A6: Hot leads | B6: =COUNTIF(Leads!$T$5:$T$304,"Hot") -> 0 | D6: Auto components (Tier 2 / Tier 3) | E6: =COUNTIF(Leads!$J$5:$J$304,D6) -> 3
A7: Warm leads | B7: =COUNTIF(Leads!$T$5:$T$304,"Warm") -> 9 | D7: Plastics, moulding and packaging | E7: =COUNTIF(Leads!$J$5:$J$304,D7) -> 3
A8: Cold leads | B8: =COUNTIF(Leads!$T$5:$T$304,"Cold") -> 10 | D8: Food processing and formulations | E8: =COUNTIF(Leads!$J$5:$J$304,D8) -> 0
A9: Won | B9: =COUNTIF(Leads!$R$5:$R$304,"Won") -> 0 | D9: Castings and forgings | E9: =COUNTIF(Leads!$J$5:$J$304,D9) -> 7
A10: Follow-ups overdue (open leads) | B10: =COUNTIFS(Leads!$V$5:$V$304,"<"&TODAY(),Leads!$V$5:$V$304,"<>",Leads!$R$5:$R$304,"<>Won",Leads!$R$5:$R$304,"<>Lost",Leads!$R$5:$R$304,"<>Not a fit") -> 0 | D10: Textiles and garments | E10: =COUNTIF(Leads!$J$5:$J$304,D10) -> 0
A11: Win rate of closed leads | B11: =IF(B9+COUNTIF(Leads!$R$5:$R$304,"Lost")=0,0,B9/(B9+COUNTIF(Leads!$R$5:$R$304,"Lost"))) -> 0 | D11: Chemicals and paints | E11: =COUNTIF(Leads!$J$5:$J$304,D11) -> 0
D12: Electricals and cables | E12: =COUNTIF(Leads!$J$5:$J$304,D12) -> 0
D13: Rubber and polymer products | E13: =COUNTIF(Leads!$J$5:$J$304,D13) -> 0
A14: By stage | B14: Leads | D14: Furniture and wood products | E14: =COUNTIF(Leads!$J$5:$J$304,D14) -> 0
A15: New | B15: =COUNTIF(Leads!$R$5:$R$304,A15) -> 19 | D15: Pharma formulations (small) | E15: =COUNTIF(Leads!$J$5:$J$304,D15) -> 0
A16: Contacted | B16: =COUNTIF(Leads!$R$5:$R$304,A16) -> 0 | D16: Other manufacturing | E16: =COUNTIF(Leads!$J$5:$J$304,D16) -> 0
A17: Demo booked | B17: =COUNTIF(Leads!$R$5:$R$304,A17) -> 0
A18: Demo done | B18: =COUNTIF(Leads!$R$5:$R$304,A18) -> 0 | D18: By lead source | E18: Leads
A19: Proposal sent | B19: =COUNTIF(Leads!$R$5:$R$304,A19) -> 0 | D19: Own research (company website) | E19: =COUNTIF(Leads!$Q$5:$Q$304,D19) -> 19
A20: Negotiation | B20: =COUNTIF(Leads!$R$5:$R$304,A20) -> 0 | D20: Referral from customer | E20: =COUNTIF(Leads!$Q$5:$Q$304,D20) -> 0
A21: Won | B21: =COUNTIF(Leads!$R$5:$R$304,A21) -> 0 | D21: CA or Tally partner | E21: =COUNTIF(Leads!$Q$5:$Q$304,D21) -> 0
A22: Lost | B22: =COUNTIF(Leads!$R$5:$R$304,A22) -> 0 | D22: Website enquiry | E22: =COUNTIF(Leads!$Q$5:$Q$304,D22) -> 0
A23: Not a fit | B23: =COUNTIF(Leads!$R$5:$R$304,A23) -> 0 | D23: Instagram / Facebook | E23: =COUNTIF(Leads!$Q$5:$Q$304,D23) -> 0
D24: LinkedIn | E24: =COUNTIF(Leads!$Q$5:$Q$304,D24) -> 0
A25: By buying intent | B25: Leads | D25: IndiaMART / TradeIndia enquiry | E25: =COUNTIF(Leads!$Q$5:$Q$304,D25) -> 0
A26: Yes, wants to decide this month | B26: =COUNTIF(Leads!$P$5:$P$304,A26) -> 0 | D26: Industry association / expo | E26: =COUNTIF(Leads!$Q$5:$Q$304,D26) -> 0
A27: Yes, this quarter | B27: =COUNTIF(Leads!$P$5:$P$304,A27) -> 0 | D27: Cold call | E27: =COUNTIF(Leads!$Q$5:$Q$304,D27) -> 0
A28: Exploring, no timeline | B28: =COUNTIF(Leads!$P$5:$P$304,A28) -> 0 | D28: WhatsApp enquiry | E28: =COUNTIF(Leads!$Q$5:$Q$304,D28) -> 0
A29: Not looking now | B29: =COUNTIF(Leads!$P$5:$P$304,A29) -> 0 | D29: Other | E29: =COUNTIF(Leads!$Q$5:$Q$304,D29) -> 0
A30: Not asked yet | B30: =COUNTIF(Leads!$P$5:$P$304,A30) -> 19

Sheet Lists
A1: Lists and scoring points
A2: Dropdown choices for the Leads sheet. Points feed the Fit score. Edit points here to change how leads are ranked.
A4: Industry | B4: Points | D4: MSME category | E4: Points | G4: Current system | H4: Points | J4: Actively looking? | K4: Points | M4: Lead source | O4: Stage | Q4: Main pain point | S4: State
A5: Engineering, fabrication and machining | B5: 40 | D5: Micro (turnover up to Rs 10 crore) | E5: 12 | G5: Tally | H5: 20 | J5: Yes, wants to decide this month | K5: 20 | M5: Own research (company website) | O5: New | Q5: Stock does not match the store | S5: Maharashtra
A6: Auto components (Tier 2 / Tier 3) | B6: 40 | D6: Small (Rs 10 to 100 crore) | E6: 20 | G6: Busy | H6: 20 | J6: Yes, this quarter | K6: 15 | M6: Referral from customer | O6: Contacted | Q6: Do not know real product cost | S6: Gujarat
A7: Plastics, moulding and packaging | B7: 32 | D7: Medium (Rs 100 to 500 crore) | E7: 10 | G7: Marg | H7: 16 | J7: Exploring, no timeline | K7: 8 | M7: CA or Tally partner | O7: Demo booked | Q7: Production tracked on paper | S7: Tamil Nadu
A8: Food processing and formulations | B8: 32 | D8: Not known | E8: 5 | G8: Excel and paper only | H8: 18 | J8: Not looking now | K8: 0 | M8: Website enquiry | O8: Demo done | Q8: Late deliveries to customers | S8: Karnataka
A9: Textiles and garments | B9: 24 | G9: Zoho / other cloud billing | H9: 12 | J9: Not asked yet | K9: 4 | M9: Instagram / Facebook | O9: Proposal sent | Q9: GST and compliance work is manual | S9: Delhi
A10: Chemicals and paints | B10: 24 | G10: Other ERP (SAP, Odoo, ERPNext) | H10: 5 | M10: LinkedIn | O10: Negotiation | Q10: Job work material not tracked | S10: Haryana
A11: Electricals and cables | B11: 24 | G11: Not known | H11: 8 | M11: IndiaMART / TradeIndia enquiry | O11: Won | Q11: Rejections and quality problems | S11: Punjab
A12: Castings and forgings | B12: 32 | M12: Industry association / expo | O12: Lost | Q12: Owner cannot see business when away | S12: Uttar Pradesh
A13: Rubber and polymer products | B13: 24 | M13: Cold call | O13: Not a fit | Q13: Outgrown Tally | S13: Rajasthan
A14: Furniture and wood products | B14: 16 | M14: WhatsApp enquiry | Q14: Other | S14: Telangana
A15: Pharma formulations (small) | B15: 16 | M15: Other | S15: Andhra Pradesh
A16: Other manufacturing | B16: 16 | S16: West Bengal
S17: Madhya Pradesh
S18: Kerala
S19: Other
A20: Assumption: the points are a starting judgement, not measured data. Industry points are the fit score on the Industries sheet times 8 (maximum 40). Category, current system and buying intent are worth up to 20 each, so the best possible Fit score is 100.
